{
  "hyper": {
    "latestRelease": {
      "url": "https://api.github.com/repos/vercel/hyper/releases/17261374",
      "assets_url": "https://api.github.com/repos/vercel/hyper/releases/17261374/assets",
      "upload_url": "https://uploads.github.com/repos/vercel/hyper/releases/17261374/assets{?name,label}",
      "html_url": "https://github.com/vercel/hyper/releases/tag/3.0.2",
      "id": 17261374,
      "author": {
        "login": "juancampa",
        "id": 1410520,
        "node_id": "MDQ6VXNlcjE0MTA1MjA=",
        "avatar_url": "https://avatars.githubusercontent.com/u/1410520?v=4",
        "gravatar_id": "",
        "url": "https://api.github.com/users/juancampa",
        "html_url": "https://github.com/juancampa",
        "followers_url": "https://api.github.com/users/juancampa/followers",
        "following_url": "https://api.github.com/users/juancampa/following{/other_user}",
        "gists_url": "https://api.github.com/users/juancampa/gists{/gist_id}",
        "starred_url": "https://api.github.com/users/juancampa/starred{/owner}{/repo}",
        "subscriptions_url": "https://api.github.com/users/juancampa/subscriptions",
        "organizations_url": "https://api.github.com/users/juancampa/orgs",
        "repos_url": "https://api.github.com/users/juancampa/repos",
        "events_url": "https://api.github.com/users/juancampa/events{/privacy}",
        "received_events_url": "https://api.github.com/users/juancampa/received_events",
        "type": "User",
        "site_admin": false
      },
      "node_id": "MDc6UmVsZWFzZTE3MjYxMzc0",
      "tag_name": "3.0.2",
      "target_commitish": "canary",
      "name": "3.0.2",
      "draft": false,
      "prerelease": false,
      "created_at": "2019-05-09T20:25:10Z",
      "published_at": "2019-05-09T20:39:39Z",
      "assets": [
        {
          "url": "https://api.github.com/repos/vercel/hyper/releases/assets/12477131",
          "id": 12477131,
          "node_id": "MDEyOlJlbGVhc2VBc3NldDEyNDc3MTMx",
          "name": "hyper-3.0.2-full.nupkg",
          "label": "",
          "uploader": {
            "login": "leo",
            "id": 6170607,
            "node_id": "MDQ6VXNlcjYxNzA2MDc=",
            "avatar_url": "https://avatars.githubusercontent.com/u/6170607?v=4",
            "gravatar_id": "",
            "url": "https://api.github.com/users/leo",
            "html_url": "https://github.com/leo",
            "followers_url": "https://api.github.com/users/leo/followers",
            "following_url": "https://api.github.com/users/leo/following{/other_user}",
            "gists_url": "https://api.github.com/users/leo/gists{/gist_id}",
            "starred_url": "https://api.github.com/users/leo/starred{/owner}{/repo}",
            "subscriptions_url": "https://api.github.com/users/leo/subscriptions",
            "organizations_url": "https://api.github.com/users/leo/orgs",
            "repos_url": "https://api.github.com/users/leo/repos",
            "events_url": "https://api.github.com/users/leo/events{/privacy}",
            "received_events_url": "https://api.github.com/users/leo/received_events",
            "type": "User",
            "site_admin": false
          },
          "content_type": "application/octet-stream",
          "state": "uploaded",
          "size": 59097612,
          "download_count": 346194,
          "created_at": "2019-05-09T20:37:27Z",
          "updated_at": "2019-05-09T20:37:29Z",
          "browser_download_url": "https://github.com/vercel/hyper/releases/download/3.0.2/hyper-3.0.2-full.nupkg"
        },
        {
          "url": "https://api.github.com/repos/vercel/hyper/releases/assets/12476241",
          "id": 12476241,
          "node_id": "MDEyOlJlbGVhc2VBc3NldDEyNDc2MjQx",
          "name": "Hyper-3.0.2-mac.zip",
          "label": "",
          "uploader": {
            "login": "leo",
            "id": 6170607,
            "node_id": "MDQ6VXNlcjYxNzA2MDc=",
            "avatar_url": "https://avatars.githubusercontent.com/u/6170607?v=4",
            "gravatar_id": "",
            "url": "https://api.github.com/users/leo",
            "html_url": "https://github.com/leo",
            "followers_url": "https://api.github.com/users/leo/followers",
            "following_url": "https://api.github.com/users/leo/following{/other_user}",
            "gists_url": "https://api.github.com/users/leo/gists{/gist_id}",
            "starred_url": "https://api.github.com/users/leo/starred{/owner}{/repo}",
            "subscriptions_url": "https://api.github.com/users/leo/subscriptions",
            "organizations_url": "https://api.github.com/users/leo/orgs",
            "repos_url": "https://api.github.com/users/leo/repos",
            "events_url": "https://api.github.com/users/leo/events{/privacy}",
            "received_events_url": "https://api.github.com/users/leo/received_events",
            "type": "User",
            "site_admin": false
          },
          "content_type": "application/zip",
          "state": "uploaded",
          "size": 53772243,
          "download_count": 4308423,
          "created_at": "2019-05-09T20:34:18Z",
          "updated_at": "2019-05-09T20:34:22Z",
          "browser_download_url": "https://github.com/vercel/hyper/releases/download/3.0.2/Hyper-3.0.2-mac.zip"
        },
        {
          "url": "https://api.github.com/repos/vercel/hyper/releases/assets/12476178",
          "id": 12476178,
          "node_id": "MDEyOlJlbGVhc2VBc3NldDEyNDc2MTc4",
          "name": "hyper-3.0.2-x86_64.AppImage",
          "label": "",
          "uploader": {
            "login": "juancampa",
            "id": 1410520,
            "node_id": "MDQ6VXNlcjE0MTA1MjA=",
            "avatar_url": "https://avatars.githubusercontent.com/u/1410520?v=4",
            "gravatar_id": "",
            "url": "https://api.github.com/users/juancampa",
            "html_url": "https://github.com/juancampa",
            "followers_url": "https://api.github.com/users/juancampa/followers",
            "following_url": "https://api.github.com/users/juancampa/following{/other_user}",
            "gists_url": "https://api.github.com/users/juancampa/gists{/gist_id}",
            "starred_url": "https://api.github.com/users/juancampa/starred{/owner}{/repo}",
            "subscriptions_url": "https://api.github.com/users/juancampa/subscriptions",
            "organizations_url": "https://api.github.com/users/juancampa/orgs",
            "repos_url": "https://api.github.com/users/juancampa/repos",
            "events_url": "https://api.github.com/users/juancampa/events{/privacy}",
            "received_events_url": "https://api.github.com/users/juancampa/received_events",
            "type": "User",
            "site_admin": false
          },
          "content_type": "application/octet-stream",
          "state": "uploaded",
          "size": 57126937,
          "download_count": 67971,
          "created_at": "2019-05-09T20:29:31Z",
          "updated_at": "2019-05-09T20:29:33Z",
          "browser_download_url": "https://github.com/vercel/hyper/releases/download/3.0.2/hyper-3.0.2-x86_64.AppImage"
        },
        {
          "url": "https://api.github.com/repos/vercel/hyper/releases/assets/12476232",
          "id": 12476232,
          "node_id": "MDEyOlJlbGVhc2VBc3NldDEyNDc2MjMy",
          "name": "Hyper-3.0.2.dmg",
          "label": "",
          "uploader": {
            "login": "leo",
            "id": 6170607,
            "node_id": "MDQ6VXNlcjYxNzA2MDc=",
            "avatar_url": "https://avatars.githubusercontent.com/u/6170607?v=4",
            "gravatar_id": "",
            "url": "https://api.github.com/users/leo",
            "html_url": "https://github.com/leo",
            "followers_url": "https://api.github.com/users/leo/followers",
            "following_url": "https://api.github.com/users/leo/following{/other_user}",
            "gists_url": "https://api.github.com/users/leo/gists{/gist_id}",
            "starred_url": "https://api.github.com/users/leo/starred{/owner}{/repo}",
            "subscriptions_url": "https://api.github.com/users/leo/subscriptions",
            "organizations_url": "https://api.github.com/users/leo/orgs",
            "repos_url": "https://api.github.com/users/leo/repos",
            "events_url": "https://api.github.com/users/leo/events{/privacy}",
            "received_events_url": "https://api.github.com/users/leo/received_events",
            "type": "User",
            "site_admin": false
          },
          "content_type": "application/octet-stream",
          "state": "uploaded",
          "size": 55633378,
          "download_count": 143786,
          "created_at": "2019-05-09T20:34:01Z",
          "updated_at": "2019-05-09T20:34:04Z",
          "browser_download_url": "https://github.com/vercel/hyper/releases/download/3.0.2/Hyper-3.0.2.dmg"
        },
        {
          "url": "https://api.github.com/repos/vercel/hyper/releases/assets/12476231",
          "id": 12476231,
          "node_id": "MDEyOlJlbGVhc2VBc3NldDEyNDc2MjMx",
          "name": "Hyper-3.0.2.dmg.blockmap",
          "label": "",
          "uploader": {
            "login": "leo",
            "id": 6170607,
            "node_id": "MDQ6VXNlcjYxNzA2MDc=",
            "avatar_url": "https://avatars.githubusercontent.com/u/6170607?v=4",
            "gravatar_id": "",
            "url": "https://api.github.com/users/leo",
            "html_url": "https://github.com/leo",
            "followers_url": "https://api.github.com/users/leo/followers",
            "following_url": "https://api.github.com/users/leo/following{/other_user}",
            "gists_url": "https://api.github.com/users/leo/gists{/gist_id}",
            "starred_url": "https://api.github.com/users/leo/starred{/owner}{/repo}",
            "subscriptions_url": "https://api.github.com/users/leo/subscriptions",
            "organizations_url": "https://api.github.com/users/leo/orgs",
            "repos_url": "https://api.github.com/users/leo/repos",
            "events_url": "https://api.github.com/users/leo/events{/privacy}",
            "received_events_url": "https://api.github.com/users/leo/received_events",
            "type": "User",
            "site_admin": false
          },
          "content_type": "application/octet-stream",
          "state": "uploaded",
          "size": 59054,
          "download_count": 125,
          "created_at": "2019-05-09T20:34:01Z",
          "updated_at": "2019-05-09T20:34:02Z",
          "browser_download_url": "https://github.com/vercel/hyper/releases/download/3.0.2/Hyper-3.0.2.dmg.blockmap"
        },
        {
          "url": "https://api.github.com/repos/vercel/hyper/releases/assets/12476252",
          "id": 12476252,
          "node_id": "MDEyOlJlbGVhc2VBc3NldDEyNDc2MjUy",
          "name": "hyper-3.0.2.x86_64.rpm",
          "label": "",
          "uploader": {
            "login": "juancampa",
            "id": 1410520,
            "node_id": "MDQ6VXNlcjE0MTA1MjA=",
            "avatar_url": "https://avatars.githubusercontent.com/u/1410520?v=4",
            "gravatar_id": "",
            "url": "https://api.github.com/users/juancampa",
            "html_url": "https://github.com/juancampa",
            "followers_url": "https://api.github.com/users/juancampa/followers",
            "following_url": "https://api.github.com/users/juancampa/following{/other_user}",
            "gists_url": "https://api.github.com/users/juancampa/gists{/gist_id}",
            "starred_url": "https://api.github.com/users/juancampa/starred{/owner}{/repo}",
            "subscriptions_url": "https://api.github.com/users/juancampa/subscriptions",
            "organizations_url": "https://api.github.com/users/juancampa/orgs",
            "repos_url": "https://api.github.com/users/juancampa/repos",
            "events_url": "https://api.github.com/users/juancampa/events{/privacy}",
            "received_events_url": "https://api.github.com/users/juancampa/received_events",
            "type": "User",
            "site_admin": false
          },
          "content_type": "application/x-redhat-package-manager",
          "state": "uploaded",
          "size": 39209145,
          "download_count": 11578,
          "created_at": "2019-05-09T20:34:49Z",
          "updated_at": "2019-05-09T20:34:51Z",
          "browser_download_url": "https://github.com/vercel/hyper/releases/download/3.0.2/hyper-3.0.2.x86_64.rpm"
        },
        {
          "url": "https://api.github.com/repos/vercel/hyper/releases/assets/12477132",
          "id": 12477132,
          "node_id": "MDEyOlJlbGVhc2VBc3NldDEyNDc3MTMy",
          "name": "hyper-Setup-3.0.2.exe",
          "label": "",
          "uploader": {
            "login": "leo",
            "id": 6170607,
            "node_id": "MDQ6VXNlcjYxNzA2MDc=",
            "avatar_url": "https://avatars.githubusercontent.com/u/6170607?v=4",
            "gravatar_id": "",
            "url": "https://api.github.com/users/leo",
            "html_url": "https://github.com/leo",
            "followers_url": "https://api.github.com/users/leo/followers",
            "following_url": "https://api.github.com/users/leo/following{/other_user}",
            "gists_url": "https://api.github.com/users/leo/gists{/gist_id}",
            "starred_url": "https://api.github.com/users/leo/starred{/owner}{/repo}",
            "subscriptions_url": "https://api.github.com/users/leo/subscriptions",
            "organizations_url": "https://api.github.com/users/leo/orgs",
            "repos_url": "https://api.github.com/users/leo/repos",
            "events_url": "https://api.github.com/users/leo/events{/privacy}",
            "received_events_url": "https://api.github.com/users/leo/received_events",
            "type": "User",
            "site_admin": false
          },
          "content_type": "application/octet-stream",
          "state": "uploaded",
          "size": 60004048,
          "download_count": 556881,
          "created_at": "2019-05-09T20:37:27Z",
          "updated_at": "2019-05-09T20:37:29Z",
          "browser_download_url": "https://github.com/vercel/hyper/releases/download/3.0.2/hyper-Setup-3.0.2.exe"
        },
        {
          "url": "https://api.github.com/repos/vercel/hyper/releases/assets/12476220",
          "id": 12476220,
          "node_id": "MDEyOlJlbGVhc2VBc3NldDEyNDc2MjIw",
          "name": "hyper_3.0.2_amd64.deb",
          "label": "",
          "uploader": {
            "login": "juancampa",
            "id": 1410520,
            "node_id": "MDQ6VXNlcjE0MTA1MjA=",
            "avatar_url": "https://avatars.githubusercontent.com/u/1410520?v=4",
            "gravatar_id": "",
            "url": "https://api.github.com/users/juancampa",
            "html_url": "https://github.com/juancampa",
            "followers_url": "https://api.github.com/users/juancampa/followers",
            "following_url": "https://api.github.com/users/juancampa/following{/other_user}",
            "gists_url": "https://api.github.com/users/juancampa/gists{/gist_id}",
            "starred_url": "https://api.github.com/users/juancampa/starred{/owner}{/repo}",
            "subscriptions_url": "https://api.github.com/users/juancampa/subscriptions",
            "organizations_url": "https://api.github.com/users/juancampa/orgs",
            "repos_url": "https://api.github.com/users/juancampa/repos",
            "events_url": "https://api.github.com/users/juancampa/events{/privacy}",
            "received_events_url": "https://api.github.com/users/juancampa/received_events",
            "type": "User",
            "site_admin": false
          },
          "content_type": "application/octet-stream",
          "state": "uploaded",
          "size": 39169196,
          "download_count": 111003,
          "created_at": "2019-05-09T20:32:52Z",
          "updated_at": "2019-05-09T20:32:53Z",
          "browser_download_url": "https://github.com/vercel/hyper/releases/download/3.0.2/hyper_3.0.2_amd64.deb"
        },
        {
          "url": "https://api.github.com/repos/vercel/hyper/releases/assets/12476214",
          "id": 12476214,
          "node_id": "MDEyOlJlbGVhc2VBc3NldDEyNDc2MjE0",
          "name": "hyper_3.0.2_amd64.snap",
          "label": "",
          "uploader": {
            "login": "juancampa",
            "id": 1410520,
            "node_id": "MDQ6VXNlcjE0MTA1MjA=",
            "avatar_url": "https://avatars.githubusercontent.com/u/1410520?v=4",
            "gravatar_id": "",
            "url": "https://api.github.com/users/juancampa",
            "html_url": "https://github.com/juancampa",
            "followers_url": "https://api.github.com/users/juancampa/followers",
            "following_url": "https://api.github.com/users/juancampa/following{/other_user}",
            "gists_url": "https://api.github.com/users/juancampa/gists{/gist_id}",
            "starred_url": "https://api.github.com/users/juancampa/starred{/owner}{/repo}",
            "subscriptions_url": "https://api.github.com/users/juancampa/subscriptions",
            "organizations_url": "https://api.github.com/users/juancampa/orgs",
            "repos_url": "https://api.github.com/users/juancampa/repos",
            "events_url": "https://api.github.com/users/juancampa/events{/privacy}",
            "received_events_url": "https://api.github.com/users/juancampa/received_events",
            "type": "User",
            "site_admin": false
          },
          "content_type": "application/octet-stream",
          "state": "uploaded",
          "size": 113143808,
          "download_count": 567,
          "created_at": "2019-05-09T20:31:31Z",
          "updated_at": "2019-05-09T20:31:38Z",
          "browser_download_url": "https://github.com/vercel/hyper/releases/download/3.0.2/hyper_3.0.2_amd64.snap"
        },
        {
          "url": "https://api.github.com/repos/vercel/hyper/releases/assets/12476253",
          "id": 12476253,
          "node_id": "MDEyOlJlbGVhc2VBc3NldDEyNDc2MjUz",
          "name": "latest-linux.yml",
          "label": "",
          "uploader": {
            "login": "juancampa",
            "id": 1410520,
            "node_id": "MDQ6VXNlcjE0MTA1MjA=",
            "avatar_url": "https://avatars.githubusercontent.com/u/1410520?v=4",
            "gravatar_id": "",
            "url": "https://api.github.com/users/juancampa",
            "html_url": "https://github.com/juancampa",
            "followers_url": "https://api.github.com/users/juancampa/followers",
            "following_url": "https://api.github.com/users/juancampa/following{/other_user}",
            "gists_url": "https://api.github.com/users/juancampa/gists{/gist_id}",
            "starred_url": "https://api.github.com/users/juancampa/starred{/owner}{/repo}",
            "subscriptions_url": "https://api.github.com/users/juancampa/subscriptions",
            "organizations_url": "https://api.github.com/users/juancampa/orgs",
            "repos_url": "https://api.github.com/users/juancampa/repos",
            "events_url": "https://api.github.com/users/juancampa/events{/privacy}",
            "received_events_url": "https://api.github.com/users/juancampa/received_events",
            "type": "User",
            "site_admin": false
          },
          "content_type": "text/yaml",
          "state": "uploaded",
          "size": 374,
          "download_count": 617,
          "created_at": "2019-05-09T20:34:51Z",
          "updated_at": "2019-05-09T20:34:51Z",
          "browser_download_url": "https://github.com/vercel/hyper/releases/download/3.0.2/latest-linux.yml"
        },
        {
          "url": "https://api.github.com/repos/vercel/hyper/releases/assets/12476244",
          "id": 12476244,
          "node_id": "MDEyOlJlbGVhc2VBc3NldDEyNDc2MjQ0",
          "name": "latest-mac.yml",
          "label": "",
          "uploader": {
            "login": "leo",
            "id": 6170607,
            "node_id": "MDQ6VXNlcjYxNzA2MDc=",
            "avatar_url": "https://avatars.githubusercontent.com/u/6170607?v=4",
            "gravatar_id": "",
            "url": "https://api.github.com/users/leo",
            "html_url": "https://github.com/leo",
            "followers_url": "https://api.github.com/users/leo/followers",
            "following_url": "https://api.github.com/users/leo/following{/other_user}",
            "gists_url": "https://api.github.com/users/leo/gists{/gist_id}",
            "starred_url": "https://api.github.com/users/leo/starred{/owner}{/repo}",
            "subscriptions_url": "https://api.github.com/users/leo/subscriptions",
            "organizations_url": "https://api.github.com/users/leo/orgs",
            "repos_url": "https://api.github.com/users/leo/repos",
            "events_url": "https://api.github.com/users/leo/events{/privacy}",
            "received_events_url": "https://api.github.com/users/leo/received_events",
            "type": "User",
            "site_admin": false
          },
          "content_type": "text/yaml",
          "state": "uploaded",
          "size": 503,
          "download_count": 139,
          "created_at": "2019-05-09T20:34:22Z",
          "updated_at": "2019-05-09T20:34:22Z",
          "browser_download_url": "https://github.com/vercel/hyper/releases/download/3.0.2/latest-mac.yml"
        },
        {
          "url": "https://api.github.com/repos/vercel/hyper/releases/assets/12477130",
          "id": 12477130,
          "node_id": "MDEyOlJlbGVhc2VBc3NldDEyNDc3MTMw",
          "name": "RELEASES",
          "label": "",
          "uploader": {
            "login": "leo",
            "id": 6170607,
            "node_id": "MDQ6VXNlcjYxNzA2MDc=",
            "avatar_url": "https://avatars.githubusercontent.com/u/6170607?v=4",
            "gravatar_id": "",
            "url": "https://api.github.com/users/leo",
            "html_url": "https://github.com/leo",
            "followers_url": "https://api.github.com/users/leo/followers",
            "following_url": "https://api.github.com/users/leo/following{/other_user}",
            "gists_url": "https://api.github.com/users/leo/gists{/gist_id}",
            "starred_url": "https://api.github.com/users/leo/starred{/owner}{/repo}",
            "subscriptions_url": "https://api.github.com/users/leo/subscriptions",
            "organizations_url": "https://api.github.com/users/leo/orgs",
            "repos_url": "https://api.github.com/users/leo/repos",
            "events_url": "https://api.github.com/users/leo/events{/privacy}",
            "received_events_url": "https://api.github.com/users/leo/received_events",
            "type": "User",
            "site_admin": false
          },
          "content_type": "application/octet-stream",
          "state": "uploaded",
          "size": 75,
          "download_count": 32057,
          "created_at": "2019-05-09T20:37:27Z",
          "updated_at": "2019-05-09T20:37:27Z",
          "browser_download_url": "https://github.com/vercel/hyper/releases/download/3.0.2/RELEASES"
        }
      ],
      "tarball_url": "https://api.github.com/repos/vercel/hyper/tarball/3.0.2",
      "zipball_url": "https://api.github.com/repos/vercel/hyper/zipball/3.0.2",
      "body_html": "<p><g-emoji class=\"g-emoji\" alias=\"arrow_upper_right\" fallback-src=\"https://github.githubassets.com/images/icons/emoji/unicode/2197.png\">↗️</g-emoji>Improve migration experience to Hyper 3</p>\n<h3>Patches</h3>\n<ul>\n<li>fix(config): add migration path from Hyper2 config location to Hyper3: <a class=\"issue-link js-issue-link\" data-error-text=\"Failed to load title\" data-id=\"440914899\" data-permission-text=\"Title is private\" data-url=\"https://github.com/vercel/hyper/issues/3610\" data-hovercard-type=\"pull_request\" data-hovercard-url=\"/vercel/hyper/pull/3610/hovercard\" href=\"https://github.com/vercel/hyper/pull/3610\">#3610</a></li>\n<li>fix(cli): fix 3.0 compatibility for CLI: <a class=\"issue-link js-issue-link\" data-error-text=\"Failed to load title\" data-id=\"441932113\" data-permission-text=\"Title is private\" data-url=\"https://github.com/vercel/hyper/issues/3636\" data-hovercard-type=\"pull_request\" data-hovercard-url=\"/vercel/hyper/pull/3636/hovercard\" href=\"https://github.com/vercel/hyper/pull/3636\">#3636</a></li>\n<li>Ignore line endings when comparing config file against default: <a class=\"issue-link js-issue-link\" data-error-text=\"Failed to load title\" data-id=\"442372722\" data-permission-text=\"Title is private\" data-url=\"https://github.com/vercel/hyper/issues/3645\" data-hovercard-type=\"pull_request\" data-hovercard-url=\"/vercel/hyper/pull/3645/hovercard\" href=\"https://github.com/vercel/hyper/pull/3645\">#3645</a></li>\n<li>Simplify migration to avoid handling edge cases : <a class=\"issue-link js-issue-link\" data-error-text=\"Failed to load title\" data-id=\"442261197\" data-permission-text=\"Title is private\" data-url=\"https://github.com/vercel/hyper/issues/3643\" data-hovercard-type=\"pull_request\" data-hovercard-url=\"/vercel/hyper/pull/3643/hovercard\" href=\"https://github.com/vercel/hyper/pull/3643\">#3643</a></li>\n</ul>"
    },
    "latestReleaseFetchedAt": "2021-05-09T12:07:05.637Z"
  }
}
